odoo/addons/web_ir_actions_act_multi/README.rst
odoo/addons/web_ir_actions_act_multi/__init__.py
odoo/addons/web_ir_actions_act_multi/__manifest__.py
odoo/addons/web_ir_actions_act_multi/i18n/ca.po
odoo/addons/web_ir_actions_act_multi/i18n/es.po
odoo/addons/web_ir_actions_act_multi/i18n/pt_BR.po
odoo/addons/web_ir_actions_act_multi/i18n/web_ir_actions_act_multi.pot
odoo/addons/web_ir_actions_act_multi/i18n/zh_CN.po
odoo/addons/web_ir_actions_act_multi/readme/CONTRIBUTORS.rst
odoo/addons/web_ir_actions_act_multi/readme/DESCRIPTION.rst
odoo/addons/web_ir_actions_act_multi/readme/USAGE.rst
odoo/addons/web_ir_actions_act_multi/static/description/icon.png
odoo/addons/web_ir_actions_act_multi/static/description/index.html
odoo/addons/web_ir_actions_act_multi/static/src/js/web_ir_actions_act_multi.js
odoo/addons/web_ir_actions_act_multi/views/web_ir_actions_act_multi.xml
odoo12_addon_web_ir_actions_act_multi-12.0.1.0.2.dist-info/METADATA
odoo12_addon_web_ir_actions_act_multi-12.0.1.0.2.dist-info/WHEEL
odoo12_addon_web_ir_actions_act_multi-12.0.1.0.2.dist-info/top_level.txt
odoo12_addon_web_ir_actions_act_multi-12.0.1.0.2.dist-info/RECORD
